odoo/addons/product_harmonized_system_stock/README.rst
odoo/addons/product_harmonized_system_stock/__init__.py
odoo/addons/product_harmonized_system_stock/__manifest__.py
odoo/addons/product_harmonized_system_stock/i18n/es.po
odoo/addons/product_harmonized_system_stock/i18n/fr.po
odoo/addons/product_harmonized_system_stock/i18n/fr_FR.po
odoo/addons/product_harmonized_system_stock/i18n/hr.po
odoo/addons/product_harmonized_system_stock/i18n/it.po
odoo/addons/product_harmonized_system_stock/i18n/product_harmonized_system_stock.pot
odoo/addons/product_harmonized_system_stock/readme/CONTRIBUTORS.md
odoo/addons/product_harmonized_system_stock/readme/CREDITS.md
odoo/addons/product_harmonized_system_stock/readme/DESCRIPTION.md
odoo/addons/product_harmonized_system_stock/static/description/icon.png
odoo/addons/product_harmonized_system_stock/static/description/index.html
odoo/addons/product_harmonized_system_stock/views/hs_code_menu.xml
odoo_addon_product_harmonized_system_stock-19.0.1.0.0.2.dist-info/METADATA
odoo_addon_product_harmonized_system_stock-19.0.1.0.0.2.dist-info/WHEEL
odoo_addon_product_harmonized_system_stock-19.0.1.0.0.2.dist-info/top_level.txt
odoo_addon_product_harmonized_system_stock-19.0.1.0.0.2.dist-info/RECORD
