Metadata-Version: 2.1
Name: odoo-addon-product_harmonized_system_stock
Version: 19.0.1.0.0.2
Requires-Dist: odoo-addon-product_harmonized_system==19.0.*
Requires-Dist: odoo==19.0.*
Summary: Adds a menu entry for H.S. codes
Home-page: https://github.com/OCA/intrastat-extrastat
License: AGPL-3
Author: Akretion, Odoo Community Association (OCA)
Author-email: support@odoo-community.org
Classifier: Programming Language :: Python
Classifier: Framework :: Odoo
Classifier: Framework :: Odoo :: 19.0
Classifier: License :: OSI Approved :: GNU Affero General Public License v3
